pydynamics/__init__.py
pydynamics/client.py
pydynamics/querybuilder.py
pydynamics/token.py
pydynamics-0.0.10.dist-info/LICENSE
pydynamics-0.0.10.dist-info/METADATA
pydynamics-0.0.10.dist-info/WHEEL
pydynamics-0.0.10.dist-info/top_level.txt
pydynamics-0.0.10.dist-info/RECORD
