Metadata-Version: 2.1
Name: pydynamics
Version: 0.0.10
Summary: Talk to On-Prem Dynamics CRM
Home-page: https://github.com/dangoscomb/pydynamics
Author: Dan Goscomb
Author-email: dan@flowplex.co.uk
Classifier: Programming Language :: Python :: 3
Classifier: License :: OSI Approved :: MIT License
Classifier: Operating System :: OS Independent
Requires-Python: >=3
License-File: LICENSE
Requires-Dist: lxml
Requires-Dist: requests
